nanoroute-2.0.5.dist-info/RECORD
nanoroute-2.0.5.dist-info/WHEEL
nanoroute-2.0.5.dist-info/entry_points.txt
nanoroute-2.0.5.dist-info/METADATA
nanoroute-2.0.5.dist-info/licenses/License
nanoroute-2.0.5.data/platlib/nanoroute.so
nanoroute-2.0.5.data/platlib/nanoroute.pyi
