Metadata-Version: 2.4
Name: nanoroute
Version: 2.0.5
Summary: Small, fast, HTTP URL router
Keywords: WSGI
Author-Email: Vito Gamberini <vito@gamberini.email>
License-Expression: CC0-1.0
License-File: License
Classifier: Development Status :: 5 - Production/Stable
Classifier: Programming Language :: Python :: 3
Classifier: Programming Language :: Python :: 3.13
Classifier: Programming Language :: Python :: 3.14
Classifier: Operating System :: POSIX :: Linux
Classifier: Operating System :: Microsoft :: Windows
Classifier: Operating System :: MacOS
Project-URL: Documentation, https://nanoroute.dev
Requires-Python: >=3.13
